[
  
  {
    "name": "Parkivia - Parking Lot Aggregator",
    "desc": "Full-Stack Instagram clone built using MERN stack and realtime chat with the help of socket.iO",
    "image": "./assets/images/abcdf.png",
    "category": "mern",
    "links": {
      "view": "./projects/parkivia.html",
      "code": "https://github.com/harshit7045/Parking-service-aggregator-.git"
    }
  },
  {
    "name": "OSInt Site",
    "desc": "Full-Stack OSint site to get phone number details,email details and reverse image search",
    "image": "./assets/images/image.png",
    "category": "mern",
    "links": {
      "view": "./projects/OSint.html",
      "code": "https://github.com/harshit7045/OSint-SaaS"
    }
  },
  {
    "name": "Automted pc cooling system",
    "desc": "A adapter to turn maual pc coolling system into automatic cooling system using aurdino and Python drivers" ,
    "image": "./assets/images/pcfan.png",
    "category": "Hardware and Python",
    "links": {
      "view": "",
      "code": "https://github.com/harshit7045/Automated-cooling-fan-adapter"
    }
  }

]
